forge/__init__.py
forge/auth.py
forge/base.py
forge/decorators.py
forge/errors.py
forge/forge.py
forge/forge_async.py
forge/urls.py
forge/api/__init__.py
forge/api/adm.py
forge/api/ahq.py
forge/api/dm.py
forge/api/hq.py
forge/extra/__init__.py
forge/extra/decorators.py
forge/extra/urls.py
forge/session/__init__.py
forge/session/session.py
forge/utils/__init__.py
forge/utils/logger.py
forge/utils/semaphore.py
forge_python_wrapper-0.0.1b4.dist-info/LICENSE
forge_python_wrapper-0.0.1b4.dist-info/METADATA
forge_python_wrapper-0.0.1b4.dist-info/WHEEL
forge_python_wrapper-0.0.1b4.dist-info/top_level.txt
forge_python_wrapper-0.0.1b4.dist-info/RECORD
