Metadata-Version: 2.1
Name: forge-python-wrapper
Version: 0.0.1b4
Summary: An synchronous and asynchronous Forge API Wrapper for the Autodesk Forge API
Home-page: https://github.com/lfparis/forge-python-wrapper
Author: Luis Felipe Paris
Author-email: lfparis@gmail.com
License: The MIT License (MIT)
Keywords: forge,autodesk,api,async,async.io
Platform: UNKNOWN
Classifier: Development Status :: 2 - Pre-Alpha
Classifier: Environment :: Console
Classifier: Framework :: AsyncIO
Classifier: Intended Audience :: Developers
Classifier: Programming Language :: Python
Classifier: Topic :: Software Development
Classifier: Programming Language :: Python :: 3.7
Classifier: Programming Language :: Python :: 3.8
Classifier: Programming Language :: Python :: Implementation :: CPython
Requires-Python: !=2.7.*, !=3.0.*, !=3.1.*, !=3.2.*, !=3.3.*, !=3.4.*, !=3.5.*, !=3.6.*
Requires-Dist: aiohttp
Requires-Dist: requests
Requires-Dist: selenium
Requires-Dist: chromedriver-autoinstaller
Requires-Dist: tqdm
